LICENSE.txt
README.md
setup.cfg
setup.py
game_simulator/__init__.py
game_simulator/simulation.py
game_simulator.egg-info/PKG-INFO
game_simulator.egg-info/SOURCES.txt
game_simulator.egg-info/dependency_links.txt
game_simulator.egg-info/requires.txt
game_simulator.egg-info/top_level.txt