Metadata-Version: 2.1
Name: game-simulator
Version: 0.9.1
Summary: A Python library that simulates agent interactions in normal-form games, uncovering how strategies evolve and adapt over time.
Home-page: https://github.com/ankur-tutlani/game-simulator
Download-URL: https://github.com/ankur-tutlani/game-simulator/archive/refs/tags/v_09.1.tar.gz
Author: ankurtutlani
Author-email: ankur.tutlani@gmail.com
License: MIT
Keywords: game theory,evolution,multi-agents,equilibrium,simulation,agent-based modeling,game dynamics,norms
Classifier: Development Status :: 3 - Alpha
Classifier: Intended Audience :: Developers
Classifier: Topic :: Software Development :: Build Tools
Classifier: License :: OSI Approved :: MIT License
Classifier: Programming Language :: Python :: 3.11
License-File: LICENSE.txt
